pulumi_ise/__init__.py
pulumi_ise/_utilities.py
pulumi_ise/provider.py
pulumi_ise/pulumi-plugin.json
pulumi_ise/py.typed
pulumi_ise/config/__init__.py
pulumi_ise/config/__init__.pyi
pulumi_ise/config/vars.py
pulumi_ise/deviceadmin/__init__.py
pulumi_ise/deviceadmin/_inputs.py
pulumi_ise/deviceadmin/allowed_protocols_tacacs.py
pulumi_ise/deviceadmin/authentication_rule.py
pulumi_ise/deviceadmin/authentication_rule_update_rank.py
pulumi_ise/deviceadmin/authentication_rule_update_ranks.py
pulumi_ise/deviceadmin/authorization_exception_rule.py
pulumi_ise/deviceadmin/authorization_exception_rule_update_rank.py
pulumi_ise/deviceadmin/authorization_exception_rule_update_ranks.py
pulumi_ise/deviceadmin/authorization_global_exception_rule.py
pulumi_ise/deviceadmin/authorization_global_exception_rule_update_rank.py
pulumi_ise/deviceadmin/authorization_global_exception_rule_update_ranks.py
pulumi_ise/deviceadmin/authorization_rule.py
pulumi_ise/deviceadmin/authorization_rule_update_rank.py
pulumi_ise/deviceadmin/authorization_rule_update_ranks.py
pulumi_ise/deviceadmin/condition.py
pulumi_ise/deviceadmin/get_allowed_protocols_tacacs.py
pulumi_ise/deviceadmin/get_authentication_rule.py
pulumi_ise/deviceadmin/get_authorization_exception_rule.py
pulumi_ise/deviceadmin/get_authorization_global_exception_rule.py
pulumi_ise/deviceadmin/get_authorization_rule.py
pulumi_ise/deviceadmin/get_condition.py
pulumi_ise/deviceadmin/get_policy_set.py
pulumi_ise/deviceadmin/get_tacacs_command_set.py
pulumi_ise/deviceadmin/get_tacacs_profile.py
pulumi_ise/deviceadmin/get_time_and_date_condition.py
pulumi_ise/deviceadmin/outputs.py
pulumi_ise/deviceadmin/policy_set.py
pulumi_ise/deviceadmin/policy_set_update_rank.py
pulumi_ise/deviceadmin/policy_set_update_ranks.py
pulumi_ise/deviceadmin/tacacs_command_set.py
pulumi_ise/deviceadmin/tacacs_profile.py
pulumi_ise/deviceadmin/time_and_date_condition.py
pulumi_ise/identitymanagement/__init__.py
pulumi_ise/identitymanagement/_inputs.py
pulumi_ise-0.2.7.dist-info/METADATA
pulumi_ise-0.2.7.dist-info/WHEEL
pulumi_ise-0.2.7.dist-info/top_level.txt
pulumi_ise-0.2.7.dist-info/RECORD
